niltech/Arduino.py
niltech/DHT11.py
niltech/__init__.py
niltech/way2sms.py
niltech-0.4.dist-info/DESCRIPTION.rst
niltech-0.4.dist-info/METADATA
niltech-0.4.dist-info/RECORD
niltech-0.4.dist-info/WHEEL
niltech-0.4.dist-info/metadata.json
niltech-0.4.dist-info/top_level.txt
