Metadata-Version: 2.0
Name: niltech
Version: 0.4
Summary: A various purpose library intended to be used in Raspberry pi workshops
Home-page: UNKNOWN
Author: Vaibhav VK - Niltech
Author-email: vaibhav@niltech.in
License: UNKNOWN
Keywords: Arduino,getPort,readData,extractData,read,DHT11.read,Arduino.getPort,Arduino.readData,Arduino.extractData,way2sms,way2sms.sendmessage()
Platform: UNKNOWN
